[{"__type__":"cc.SpriteFrame","content":{"name":"part22","texture":"bf2IB5IEJC3I6lGUa/BSjc","rect":[423,388,978,515],"offset":[30,206.5],"originalSize":[1764,1704],"capInsets":[0,0,0,0]}},{"__type__":"cc.SpriteFrame","content":{"name":"part11","texture":"2aaD/HYsxLcKFOmzNZp/7a","rect":[423,388,980,516],"offset":[31,206],"originalSize":[1764,1704],"capInsets":[0,0,0,0]}},[{"__type__":"cc.Prefab","_name":"partUI","data":{"__id__":1}},{"__type__":"cc.Node","_name":"partUI","_children":[{"__id__":2}],"_components":[{"__type__":"cc.Widget","node":{"__id__":1},"_alignFlags":45},{"__type__":"80fa4Lvn+FBEInBX6AJdfbI","node":{"__id__":1}}],"_prefab":{"__type__":"cc.PrefabInfo","root":{"__id__":1},"asset":{"__uuid__":"c6L//Dr69KsY3yV0h2GY6v"},"fileId":"7eqs1K5NRP/o1fISbgL/i5"},"_contentSize":{"__type__":"cc.Size","width":1080,"height":720},"_trs":{"__type__":"TypedArray","ctor":"Float64Array","array":[0,0,0,0,0,0,1,1,1,1]},"_groupIndex":3,"groupIndex":3},{"__type__":"cc.Node","_name":"bg","_parent":{"__id__":1},"_children":[{"__id__":3},{"__id__":4},{"__id__":5}],"_components":[{"__type__":"cc.Sprite","_name":"bg<Sprite>","node":{"__id__":2},"_materials":[{"__uuid__":"ecpdLyjvZBwrvm+cedCcQy"}]},{"__type__":"cc.Widget","node":{"__id__":2},"_alignFlags":45,"_originalWidth":918,"_originalHeight":725}],"_prefab":{"__type__":"cc.PrefabInfo","root":{"__id__":1},"asset":{"__uuid__":"c6L//Dr69KsY3yV0h2GY6v"},"fileId":"e0kl6/qtdFl5ep9QQvhxNo"},"_contentSize":{"__type__":"cc.Size","width":1080,"height":720},"_trs":{"__type__":"TypedArray","ctor":"Float64Array","array":[0,0,0,0,0,0,1,1,1,1]},"_groupIndex":3,"groupIndex":3},{"__type__":"cc.Node","_name":"transparency","_parent":{"__id__":2},"_components":[{"__type__":"cc.Sprite","_name":"transparency<Sprite>","node":{"__id__":3},"_materials":[{"__uuid__":"ecpdLyjvZBwrvm+cedCcQy"}],"_spriteFrame":{"__uuid__":"adHxcvAANDrKvHVjum7KX9"},"_type":1,"_sizeMode":0},{"__type__":"cc.Widget","node":{"__id__":3},"_alignFlags":45,"_originalWidth":676,"_originalHeight":534},{"__type__":"cc.Button","node":{"__id__":3}}],"_prefab":{"__type__":"cc.PrefabInfo","root":{"__id__":1},"asset":{"__uuid__":"c6L//Dr69KsY3yV0h2GY6v"},"fileId":"d9j6L5PDxBa4kjlZ6LQl1I"},"_contentSize":{"__type__":"cc.Size","width":1080,"height":720},"_anchorPoint":{"__type__":"cc.Vec2","x":0.5174396728794635,"y":0.4679843962761651},"_trs":{"__type__":"TypedArray","ctor":"Float64Array","array":[18.834846709820567,-23.051234681161134,0,0,0,0,1,1,1,0]},"_groupIndex":3,"groupIndex":3},{"__type__":"cc.Node","_name":"part1","_parent":{"__id__":2},"_components":[{"__type__":"cc.Sprite","node":{"__id__":4},"_materials":[{"__uuid__":"ecpdLyjvZBwrvm+cedCcQy"}],"_spriteFrame":{"__uuid__":"b0BYqtMjBIN4FKiN0jfOS/"},"_sizeMode":0},{"__type__":"cc.Widget","node":{"__id__":4},"_alignFlags":41,"_left":361.663,"_right":378.337,"_top":108.125,"_originalWidth":563},{"__type__":"cc.Button","node":{"__id__":4},"duration":0.15,"clickEvents":[{"__type__":"cc.ClickEvent","target":{"__id__":1},"_componentId":"80fa4Lvn+FBEInBX6AJdfbI","handler":"hide"}],"_N$transition":3,"transition":3}],"_prefab":{"__type__":"cc.PrefabInfo","root":{"__id__":1},"asset":{"__uuid__":"c6L//Dr69KsY3yV0h2GY6v"},"fileId":"12wrpiNgZFTYPmjmgeEqJ7"},"_contentSize":{"__type__":"cc.Size","width":340,"height":175},"_trs":{"__type__":"TypedArray","ctor":"Float64Array","array":[-8.336999999999989,164.375,0,0,0,0,1,1,1,0]},"_groupIndex":3,"groupIndex":3},{"__type__":"cc.Node","_name":"part2","_parent":{"__id__":2},"_components":[{"__type__":"cc.Sprite","node":{"__id__":5},"_materials":[{"__uuid__":"ecpdLyjvZBwrvm+cedCcQy"}],"_spriteFrame":{"__uuid__":"2eSu4ZwiBFmbYBomsacznp"},"_sizeMode":0},{"__type__":"cc.Widget","node":{"__id__":5},"_alignFlags":41,"_left":361.4442164,"_right":378.5557836,"_top":421.950506886458,"_originalWidth":277}],"_prefab":{"__type__":"cc.PrefabInfo","root":{"__id__":1},"asset":{"__uuid__":"c6L//Dr69KsY3yV0h2GY6v"},"fileId":"3fIozMtb5C77t87V1ezw9M"},"_contentSize":{"__type__":"cc.Size","width":340,"height":175},"_trs":{"__type__":"TypedArray","ctor":"Float64Array","array":[-8.555783599999984,-149.45050688645802,0,0,0,0,1,1,1,1]},"_groupIndex":3,"groupIndex":3}]]